binarybrain/__init__.py
binarybrain/core.cp39-win_amd64.exp
binarybrain/core.cp39-win_amd64.lib
binarybrain/core.cp39-win_amd64.pyd
binarybrain/dtype.py
binarybrain/frame_buffer.py
binarybrain/hls.py
binarybrain/losses.py
binarybrain/metrics.py
binarybrain/models.py
binarybrain/object.py
binarybrain/optimizer.py
binarybrain/storage.py
binarybrain/system.py
binarybrain/tensor.py
binarybrain/variables.py
binarybrain/verilog.py
binarybrain/cuda/AverageLut.cu
binarybrain/cuda/BatchNormalization.cu
binarybrain/cuda/Binarize.cu
binarybrain/cuda/BinaryLut6.cu
binarybrain/cuda/BinaryToReal.cu
binarybrain/cuda/BitEncode.cu
binarybrain/cuda/BitError.cu
binarybrain/cuda/Col2Im.cu
binarybrain/cuda/Common.cuh
binarybrain/cuda/ConvBitToReal.cu
binarybrain/cuda/DepthwiseDenseAffine.cu
binarybrain/cuda/DifferentiableLut.cu
binarybrain/cuda/FrameBufferCopy.cu
binarybrain/cuda/HardTanh.cu
binarybrain/cuda/Im2Col.cu
binarybrain/cuda/LocalHeap.cu
binarybrain/cuda/LossMeanSquaredError.cu
binarybrain/cuda/LossSoftmaxCrossEntropy.cu
binarybrain/cuda/Manager.cu
binarybrain/cuda/MatrixColwiseMeanVar.cu
binarybrain/cuda/MatrixColwiseSum.cu
binarybrain/cuda/MatrixRowwiseSetVector.cu
binarybrain/cuda/MaxLut.cu
binarybrain/cuda/MaxPooling.cu
binarybrain/cuda/MetricsCategoricalAccuracy.cu
binarybrain/cuda/MicroMlp.cu
binarybrain/cuda/OptimizerAdam.cu
binarybrain/cuda/ReLU.cu
binarybrain/cuda/RealToBinary.cu
binarybrain/cuda/Shuffle.cu
binarybrain/cuda/ShuffleModulation.cu
binarybrain/cuda/Sigmoid.cu
binarybrain/cuda/StochasticBatchNormalization.cu
binarybrain/cuda/StochasticLut.cu
binarybrain/cuda/StochasticLut.cuh
binarybrain/cuda/StochasticMaxPooling.cu
binarybrain/cuda/UpSampling.cu
binarybrain/cuda/Utility.cu
binarybrain/cuda/Vector.cu
binarybrain/include/bb/Activation.h
binarybrain/include/bb/Assert.h
binarybrain/include/bb/AverageLut.h
binarybrain/include/bb/AveragePooling.h
binarybrain/include/bb/BackpropagatedBatchNormalization.h
binarybrain/include/bb/BatchNormalization.h
binarybrain-4.3.2.dist-info/METADATA
binarybrain-4.3.2.dist-info/WHEEL
binarybrain-4.3.2.dist-info/top_level.txt
binarybrain-4.3.2.dist-info/RECORD
