Metadata-Version: 2.1
Name: binarybrain
Version: 4.3.2
Summary: BinaryBrain for Python
Home-page: https://github.com/ryuz/BinaryBrain
Author: Ryuji Fuchikami
Author-email: ryuji.fuchikami@nifty.com
License: UNKNOWN
Platform: UNKNOWN
Requires-Dist: pybind11 (>=2.4)
Requires-Dist: numpy
